terrajinja/sbp/vault/kv_secret_v2.py
terrajinja_sbp_vault-0.2.1.dist-info/LICENSE
terrajinja_sbp_vault-0.2.1.dist-info/METADATA
terrajinja_sbp_vault-0.2.1.dist-info/WHEEL
terrajinja_sbp_vault-0.2.1.dist-info/top_level.txt
terrajinja_sbp_vault-0.2.1.dist-info/RECORD
