Metadata-Version: 2.1
Name: terrajinja-sbp-vault
Version: 0.2.1
Summary: Terrajinja extension for automation using cdktf
Home-page: https://gitlab/terrajinja
Author: Terrajinja Team
Author-email: int-terrajinja@schubergphilis.com
License: MIT
Classifier: Development Status :: 4 - Beta
Classifier: Intended Audience :: Developers
Classifier: License :: OSI Approved :: MIT License
Classifier: Natural Language :: English
Classifier: Programming Language :: Python :: 3.11
License-File: LICENSE
Requires-Dist: cdktf-cdktf-provider-vault >=12.1.0
Requires-Dist: random-password-generator >=2.2.0
